{
  "timestamp": "2025-09-12T17:00:37.837Z",
  "environment": {
    "node": "v20.18.2",
    "platform": "linux",
    "arch": "x64",
    "cpus": 12,
    "memory": "16GB"
  },
  "buildMetrics": {
    "buildTime": 44674,
    "buildTimeFormatted": "44.67s",
    "totalRoutes": 5,
    "staticRoutes": 5,
    "dynamicRoutes": 0,
    "staticDataRoutes": 0,
    "firstLoadJS": 607,
    "rating": "needs-improvement"
  },
  "bundleAnalysis": {
    "totalStaticSize": 2.9818547057367635,
    "totalStaticSizeFormatted": "2.98 kB",
    "chunksCount": 261,
    "largestChunks": [
      {
        "name": "vendors-4b98965a-3ea0ffc09365e464.js",
        "size": 197.1240234375,
        "sizeFormatted": "197.12 kB"
      },
      {
        "name": "react-core-36598b9c-24907994d7e8ffd7.js",
        "size": 163.80078125,
        "sizeFormatted": "163.80 kB"
      },
      {
        "name": "polyfills-42372ed130431b0a.js",
        "size": 109.955078125,
        "sizeFormatted": "109.96 kB"
      },
      {
        "name": "vendors-aa6d47da-bcee20102886cba9.js",
        "size": 55.208984375,
        "sizeFormatted": "55.21 kB"
      },
      {
        "name": "form-validation-5785018b-9f2278367f41a54e.js",
        "size": 52.0615234375,
        "sizeFormatted": "52.06 kB"
      },
      {
        "name": "common-7bc70e8b-c1f273541cd755b3.js",
        "size": 45.0849609375,
        "sizeFormatted": "45.08 kB"
      },
      {
        "name": "common-ccb8bed9-04406c015a5c7eb5.js",
        "size": 43.224609375,
        "sizeFormatted": "43.22 kB"
      },
      {
        "name": "vendors-de1750a5-52c376f06cbbb540.js",
        "size": 40.91015625,
        "sizeFormatted": "40.91 kB"
      },
      {
        "name": "common-9f2e9d12-46108032a43ea8ae.js",
        "size": 37.04296875,
        "sizeFormatted": "37.04 kB"
      },
      {
        "name": "common-59dc22c8-6fbb6c91b30df909.js",
        "size": 33.169921875,
        "sizeFormatted": "33.17 kB"
      }
    ],
    "averageChunkSize": 9.828379430076629
  },
  "runtimeMetrics": {},
  "componentMetrics": {
    "hero-section": {
      "fileSize": "6.92 kB",
      "lines": 135,
      "hasLazyLoad": false,
      "hasOptimizedImages": false,
      "usesFramerMotion": false,
      "complexity": 48
    },
    "about-section": {
      "fileSize": "22.85 kB",
      "lines": 396,
      "hasLazyLoad": false,
      "hasOptimizedImages": true,
      "usesFramerMotion": true,
      "complexity": 10
    }
  },
  "recommendations": [
    {
      "type": "bundle-size",
      "priority": "high",
      "message": "5 chunks exceed 50kB. Consider code splitting or dynamic imports."
    },
    {
      "type": "animation-optimization",
      "priority": "high",
      "message": "Component 'about-section' uses Framer Motion but is not lazy loaded."
    }
  ],
  "budgetViolations": [
    {
      "metric": "First Load JS",
      "budget": 250,
      "actual": 607,
      "exceeded": "142.8"
    },
    {
      "metric": "Build Time",
      "budget": 30,
      "actual": 44.674,
      "exceeded": "48.9"
    },
    {
      "metric": "Largest Chunk",
      "budget": 100,
      "actual": 197.1240234375,
      "exceeded": "97.1"
    }
  ],
  "summary": {
    "buildPerformance": "needs-improvement",
    "bundleSize": "poor",
    "recommendations": 2,
    "budgetViolations": 3
  }
}